district42/__init__.py
district42/_from_native.py
district42/_props.py
district42/_schema_facade.py
district42/_schema_visitor.py
district42/_version.py
district42/py.typed
district42/errors/__init__.py
district42/representor/__init__.py
district42/representor/_representor.py
district42/types/__init__.py
district42/types/_any_schema.py
district42/types/_bool_schema.py
district42/types/_bytes_schema.py
district42/types/_const_schema.py
district42/types/_date_schema.py
district42/types/_datetime_schema.py
district42/types/_dict_schema.py
district42/types/_float_schema.py
district42/types/_int_schema.py
district42/types/_list_schema.py
district42/types/_none_schema.py
district42/types/_optional.py
district42/types/_schema.py
district42/types/_str_schema.py
district42/types/_type_alias_schema.py
district42/types/_uuid4_schema.py
district42/utils/__init__.py
district42/utils/_is_ellipsis.py
district42/utils/_rollout.py
district42-1.8.0.dist-info/LICENSE.txt
district42-1.8.0.dist-info/METADATA
district42-1.8.0.dist-info/WHEEL
district42-1.8.0.dist-info/top_level.txt
district42-1.8.0.dist-info/RECORD
