Metadata-Version: 2.1
Name: district42
Version: 1.8.0
Summary: Data description language for defining data models
Home-page: https://github.com/d42-schemas/district42
Author: Nikita Tsvetkov
Author-email: tsv1@fastmail.com
License: Apache-2.0
Project-URL: Docs, https://d42.vedro.io
Project-URL: GitHub, https://github.com/d42-schemas/district42
Classifier: License :: OSI Approved :: Apache Software License
Classifier: Programming Language :: Python :: 3.8
Classifier: Programming Language :: Python :: 3.9
Classifier: Programming Language :: Python :: 3.10
Classifier: Programming Language :: Python :: 3.11
Classifier: Programming Language :: Python :: 3.12
Classifier: Typing :: Typed
Requires-Python: >=3.8
License-File: LICENSE.txt
Requires-Dist: niltype <2.0,>=0.3
